llm_multiple_choice/__init__.py
llm_multiple_choice/choice_code.py
llm_multiple_choice/choice_manager.py
llm_multiple_choice/display_format.py
llm_multiple_choice/exceptions.py
llm_multiple_choice/py.typed
llm_multiple_choice/utils.py
llm_multiple_choice-0.1.3.dist-info/LICENSE
llm_multiple_choice-0.1.3.dist-info/METADATA
llm_multiple_choice-0.1.3.dist-info/WHEEL
llm_multiple_choice-0.1.3.dist-info/RECORD
