Metadata-Version: 2.1
Name: llm-multiple-choice
Version: 0.1.3
Summary: A Python library for using Large Language Models (LLMs) to fill out multiple-choice questionnaires about chat conversations.
License: MIT
Author: Dean Thompson
Author-email: deansherthompson@gmail.com
Requires-Python: >=3.10,<3.13
Classifier: Development Status :: 4 - Beta
Classifier: Intended Audience :: Developers
Classifier: License :: OSI Approved :: MIT License
Classifier: Programming Language :: Python :: 3
Classifier: Programming Language :: Python :: 3.10
Classifier: Programming Language :: Python :: 3.11
Classifier: Programming Language :: Python :: 3.12
Classifier: Programming Language :: Python :: 3.13
Classifier: Topic :: Scientific/Engineering :: Artificial Intelligence
Classifier: Topic :: Software Development :: Libraries :: Python Modules
Classifier: Typing :: Typed
Project-URL: Bug Tracker, https://github.com/deansher/llm-multiple-choice-py/issues
Project-URL: Documentation, https://github.com/deansher/llm-multiple-choice-py#readme
Project-URL: Homepage, https://github.com/deansher/llm-multiple-choice-py
Project-URL: Source Code, https://github.com/deansher/llm-multiple-choice-py
